fal_ai_mcp/__init__.py
fal_ai_mcp/__main__.py
fal_ai_mcp/fal_ai_mcp.py
fal_ai_mcp-0.1.3.dist-info/METADATA
fal_ai_mcp-0.1.3.dist-info/WHEEL
fal_ai_mcp-0.1.3.dist-info/entry_points.txt
fal_ai_mcp-0.1.3.dist-info/RECORD
