Metadata-Version: 2.4
Name: fal-ai-mcp
Version: 0.1.3
Summary: A Model Context Protocol (MCP) server for generating images using Fal.ai's HiDream-I1-Full model
Project-URL: Homepage, https://github.com/yourusername/fal-ai-mcp
Project-URL: Bug Tracker, https://github.com/yourusername/fal-ai-mcp/issues
Author-email: Virtuoasis <kitchenbyomakase@gmail.com>
Classifier: License :: OSI Approved :: MIT License
Classifier: Operating System :: OS Independent
Classifier: Programming Language :: Python :: 3
Classifier: Topic :: Scientific/Engineering :: Artificial Intelligence
Classifier: Topic :: Software Development :: Libraries :: Python Modules
Requires-Python: >=3.10
Requires-Dist: fal-client>=0.5.9
Requires-Dist: mcp[cli]>=1.6.0
Requires-Dist: python-dotenv>=0.15.0
Requires-Dist: twine>=6.1.0
